{
    "alpha": "100",

    "special": {
        "background": "#fefefe",
        "foreground": "#000000",
        "cursor": "#000000"
    },
    "colors": {
        "color0": "#fefefe",
        "color1": "#272D4D",
        "color2": "#B83564",
        "color3": "#FF6A5A",
        "color4": "#FFB350",
        "color5": "#83B8AA",
        "color6": "#a0a0a0",
        "color7": "#000000",
        "color8": "#dadada",
        "color9": "#272D4D",
        "color10": "#B83564",
        "color11": "#FF6A5A",
        "color12": "#FFB350",
        "color13": "#83B8AA",
        "color14": "#a0a0a0",
        "color15": "#000000"
    }
}
